audioglot/__init__.py
audioglot-0.0.1.dist-info/licenses/LICENSE
audioglot-0.0.1.dist-info/METADATA
audioglot-0.0.1.dist-info/WHEEL
audioglot-0.0.1.dist-info/top_level.txt
audioglot-0.0.1.dist-info/RECORD
