Metadata-Version: 2.4
Name: audioglot
Version: 0.0.1
Summary: Transcribe and translate personal media library.
Author-email: Andrew Schaub <aschaub930@gmail.com>
Project-URL: Homepage, https://github.com/drewschaub/audioglot
Project-URL: Documentation, https://github.com/drewschaub/audioglot#readme
Project-URL: Repository, https://github.com/drewschaub/audioglot
Classifier: Programming Language :: Python :: 3
Classifier: Operating System :: OS Independent
Requires-Python: >=3.8
License-File: LICENSE
Dynamic: license-file
